rccnlp/__init__.py
rccnlp/sentiment.py
rccnlp/dic/pn_noun.json
rccnlp/dic/pn_wago.json
rccnlp-0.1.0.dist-info/METADATA
rccnlp-0.1.0.dist-info/WHEEL
rccnlp-0.1.0.dist-info/top_level.txt
rccnlp-0.1.0.dist-info/RECORD
